gwalk/__init__.py
gwalk/__version__.py
gwalk/optimize_likelihood_grid.py
gwalk/tools/example_script.py
gwalk/tools/NAL_event_pipeline.py
gwalk/tools/fit_catalog_samples.py
gwalk/tools/__init__.py
gwalk/tools/fit_event_loop.py
gwalk/tools/fit_likelihood_grid.py
gwalk/tools/fit_GW231123.py
gwalk/tools/plot_nal_fit.py
gwalk/catalog/catalog.py
gwalk/catalog/__init__.py
gwalk/catalog/coordinates.py
gwalk/catalog/prior/CIP_prior_functions.py
gwalk/catalog/prior/__init__.py
gwalk/catalog/prior/callister_prior.py
gwalk/catalog/prior/prior_methods.py
gwalk/density/__init__.py
gwalk/density/mesh.py
gwalk/utils/hist.py
gwalk/utils/tee.py
gwalk/utils/multivariate_normal.py
gwalk/utils/__init__.py
gwalk/mixture/mixture.py
gwalk/mixture/fixed.py
gwalk/mixture/kde.py
gwalk/mixture/__init__.py
gwalk/data/registry.py
gwalk/data/__init__.py
gwalk/data/files/hash.dat
gwalk/data/files/__init__.py
gwalk/multivariate_normal/object.py
gwalk/multivariate_normal/_gaussian_mixture_pdf.cpython-314-darwin.so
gwalk/multivariate_normal/__init__.py
gwalk/multivariate_normal/pdf.py
gwalk/multivariate_normal/_mahalanobis_distance.cpython-314-darwin.so
gwalk/multivariate_normal/_multivariate_normal_pdf_utils.cpython-314-darwin.so
gwalk/multivariate_normal/utils.py
gwalk/multivariate_normal/bounded_multivariate_normal.py
gwalk/multivariate_normal/_decomposition.cpython-314-darwin.so
gwalk/multivariate_normal/decomposition.py
gwalk/multivariate_normal/decomposition_numpy.py
gwalk/plots/axis.py
gwalk/plots/walker_plot.py
gwalk/plots/__init__.py
gwalk/plots/percentile_levels.py
gwalk/plots/likelihood_corner.py
gwalk-4.0.1.dist-info/RECORD
gwalk-4.0.1.dist-info/WHEEL
gwalk-4.0.1.dist-info/METADATA
