Metadata-Version: 2.1
Name: gwalk
Version: 4.0.1
Summary: GWALK: Gravitational Wave Approximate LiKelihood
Keywords: Gravitational Wave,Bayesian Inference
Author-Email: "V. Delfavero" <xevra86@gmail.com>
Maintainer-Email: "V. Delfavero" <xevra86@gmail.com>
License: MIT License
Classifier: Development Status :: 3 - Alpha
Classifier: Programming Language :: Python :: 3
Classifier: Operating System :: OS Independent
Classifier: Intended Audience :: Science/Research
Classifier: Topic :: Scientific/Engineering :: Astronomy
Classifier: Topic :: Scientific/Engineering :: Physics
Classifier: Topic :: Scientific/Engineering :: Information Analysis
Project-URL: Homepage, https://gitlab.com/xevra/gwalk
Project-URL: Bug tracker, https://gitlab.com/xevra/gwalk/issues
Requires-Python: >=3.12
Requires-Dist: numpy<2.4.0,>=1.21.6
Requires-Dist: matplotlib>=2.2.4
Requires-Dist: scipy>=1.5.0
Requires-Dist: h5py>=2.10.0
Requires-Dist: astropy>=4.0
Requires-Dist: basil-core>=0.1.0
Requires-Dist: gaussian-process-api>=0.6.0
Requires-Dist: xev-data>=0.1.1
